app/__init__.py
app/__main__.py
app/application.py
app/email_in_validate.py
app/email_validator.py
email_in_validator-1.0.2.dist-info/METADATA
email_in_validator-1.0.2.dist-info/WHEEL
email_in_validator-1.0.2.dist-info/entry_points.txt
email_in_validator-1.0.2.dist-info/top_level.txt
email_in_validator-1.0.2.dist-info/RECORD
