Metadata-Version: 2.1
Name: email_in_validator
Version: 1.0.2
Summary: This Python function, email_validator, checks if an input string is a valid email address
Home-page: https://github.com/Wilsonabdiel/regex-gen
Author: Abdiel Wilson
Author-email: wilsonabdiel86@gmail.com
License: MIT License
Classifier: Programming Language :: Python :: 3.8
Classifier: Operating System :: OS Independent
Requires-Python: >=3.7
Requires-Dist: click ==8.0.3
